package_list/__init__.py
package_list/__main__.py
package_list/main.py
package_list/py.typed
package_list-0.2.1.dist-info/entry_points.txt
package_list-0.2.1.dist-info/LICENSE
package_list-0.2.1.dist-info/WHEEL
package_list-0.2.1.dist-info/METADATA
package_list-0.2.1.dist-info/RECORD
